murdfpy/__init__.py
murdfpy/urdf.py
murdfpy/utils.py
murdfpy/version.py
murdfpy-0.0.23.dist-info/LICENSE
murdfpy-0.0.23.dist-info/METADATA
murdfpy-0.0.23.dist-info/WHEEL
murdfpy-0.0.23.dist-info/top_level.txt
murdfpy-0.0.23.dist-info/RECORD
